Metadata-Version: 2.1
Name: my-cdep-package-handle
Version: 0.0.0
Summary: cdep handle package.
Home-page: UNKNOWN
Author: xxx-xxxxxx
Author-email: xxx-xxxxxx@xxxxxxxxx.es
License: UNLICENSED
Platform: UNKNOWN
Classifier: Programming Language :: Python :: 3
Provides-Extra: configuration
